MANIFEST.in
README.md
setup.py
examples/.limboole
examples/MLK2
examples/arrows
examples/basic
examples/cacophony
examples/greaterthan
examples/gthard
examples/kakuro
examples/kakuro-base
examples/kakuro.py
examples/kakuro.sat
examples/little-killer
examples/magic
examples/minimal17
examples/nonunique
examples/palindrome
examples/tea
examples/test
examples/unique36
src/__init__.py
src/base_rules.py
src/comparators.py
src/compiler.py
src/grammar.lark
src/helpers.py
src/interpreter.py
src/modifiers.py
src/operators.py
src/prefixes.py
src/settings.py
src/ssc.py
src/__pycache__/__init__.cpython-310.pyc
src/__pycache__/base_rules.cpython-310.pyc
src/__pycache__/comparators.cpython-310.pyc
src/__pycache__/compiler.cpython-310.pyc
src/__pycache__/helpers.cpython-310.pyc
src/__pycache__/interpreter.cpython-310.pyc
src/__pycache__/modifiers.cpython-310.pyc
src/__pycache__/operators.cpython-310.pyc
src/__pycache__/prefixes.cpython-310.pyc
src/__pycache__/settings.cpython-310.pyc
src/__pycache__/ssc.cpython-310.pyc
ssc_compiler.egg-info/PKG-INFO
ssc_compiler.egg-info/SOURCES.txt
ssc_compiler.egg-info/dependency_links.txt
ssc_compiler.egg-info/entry_points.txt
ssc_compiler.egg-info/not-zip-safe
ssc_compiler.egg-info/requires.txt
ssc_compiler.egg-info/top_level.txt