Metadata-Version: 2.1
Name: ssc-compiler
Version: 1.0.2
Summary: Describe generalized Sudokus through simple equations. Compile programs to SAT and solve them with limboole.
Home-page: https://github.com/charludo/ssc
Author: Charlotte Hartmann Paludo
Author-email: charlotte.hartmann-paludo@stud.uni-due.de
License: UNKNOWN
Keywords: sudoku,sat,compiler,limboole
Platform: UNKNOWN
